chaosk8ext/__init__.py
chaosk8ext/deployment/__init__.py
chaosk8ext/deployment/actions.py
chaosk8ext/deployment/probes.py
chaostoolkit_chaosk8ext-0.2.0.dist-info/LICENSE
chaostoolkit_chaosk8ext-0.2.0.dist-info/METADATA
chaostoolkit_chaosk8ext-0.2.0.dist-info/WHEEL
chaostoolkit_chaosk8ext-0.2.0.dist-info/top_level.txt
chaostoolkit_chaosk8ext-0.2.0.dist-info/RECORD
