Metadata-Version: 2.1
Name: chaostoolkit-chaosk8ext
Version: 0.2.0
Summary: Chaos Toolkit k8s driver extension
Home-page: https://github.com/sky-uk/chaostoolkit-chaosk8ext
Author: Marco Masetti
Author-email: marco.masetti@sky.uk
License: Apache License Version 2.0
Platform: UNKNOWN
Classifier: Development Status :: 2 - Pre-Alpha
Classifier: Intended Audience :: Developers
Classifier: License :: Freely Distributable
Classifier: Operating System :: OS Independent
Classifier: License :: OSI Approved :: Apache Software License
Classifier: Programming Language :: Python
Classifier: Programming Language :: Python :: 3
Classifier: Programming Language :: Python :: 3.6
Classifier: Programming Language :: Python :: 3.7
Classifier: Programming Language :: Python :: 3.8
Classifier: Programming Language :: Python :: 3.9
Requires-Python: >=3.5.*
License-File: LICENSE
Requires-Dist: chaostoolkit-lib (>=1.1.2)
Requires-Dist: chaostoolkit-kubernetes (>=0.23.0)
Requires-Dist: kubernetes (>=11.0.0)
Requires-Dist: logzero (>=1.6.3)
Requires-Dist: p2.driver.k8s (>=0.3.2)
